Metadata-Version: 1.1
Name: pymetasploit
Version: 1.1
Summary: A full-fledged msfrpc library for Metasploit framework.
Home-page: https://github.com/allfro/pymetasploit
Author: Nadeem Douba
Author-email: ndouba@gmail.com
License: GPL
Download-URL: https://github.com/allfro/pymetasploit/zipball/master
Platform: UNKNOWN
